{
    "string":[
        {
            "name":"audio_control",
            "value":"Controllo audio",
            "attr":{
                "priority":"translate"
            }
        },
        {
            "name":"macro_focus_auto",
            "value":"Automatica",
            "attr":{
                "priority":"translate"
            }
        },
        {
            "name":"timer_2_seconds",
            "value":"%d secondi",
            "attr":{
                "priority":"translate"
            }
        },
        {
            "name":"video_frame_rate",
            "value":"Frequenza fotogrammi",
            "attr":{
                "priority":"translate"
            }
        },
        {
            "name":"photo_mode",
            "value":"Foto",
            "attr":{
                "priority":"translate"
            }
        },
        {
            "name":"portrait_mode",
            "value":"Ritratto",
            "attr":{
                "priority":"translate"
            }
        },
        {
            "name":"semi_collapsed_guide_change_mode",
            "value":"Scorri verso l'alto o verso il basso per passare da una modalità all'altra",
            "attr":{
                "priority":"translate"
            }
        },
        {
            "name":"night_mode",
            "value":"Notte",
            "attr":{
                "priority":"translate"
            }
        },
        {
            "name":"video_title",
            "value":"Impostazioni video",
            "attr":{
                "priority":"translate"
            }
        },
        {
            "name":"high_pixel_desc",
            "value":"AI Ultra Clarity è ideale per riprendere oggetti immobili e scenari in una buona illuminazione.",
            "attr":{
                "priority":"LT"
            }
        },
        {
            "name":"microphone_permission_desc",
            "value":"Per la registrazione di video e per abilitare il controllo audio.",
            "attr":{
                "priority":"translate"
            }
        },
        {
            "name":"shutter",
            "value":"Automatico",
            "attr":{
                "priority":"translate"
            }
        },
        {
            "name":"already_off",
            "value":"Disattivo",
            "attr":{
                "priority":"translate"
            }
        },
        {
            "name":"semi_collapsed_guide_title",
            "value":"Tutorial",
            "attr":{
                "priority":"translate"
            }
        },
        {
            "name":"app_name",
            "value":"Fotocamera",
            "attr":{
                "priority":"translate"
            }
        },
        {
            "name":"video_resolution",
            "value":"Risoluzione video",
            "attr":{
                "priority":"translate"
            }
        },
        {
            "name":"self_mirror_desp",
            "value":"Solo Fotocamera anteriore",
            "attr":{
                "priority":"translate"
            }
        },
        {
            "name":"off",
            "value":"Off",
            "attr":{
                "priority":"translate"
            }
        },
        {
            "name":"macro_focus_manual",
            "value":"Manuale",
            "attr":{
                "priority":"translate"
            }
        },
        {
            "name":"got_it",
            "value":"OK",
            "attr":{
                "priority":"translate"
            }
        },
        {
            "name":"pic_title",
            "value":"Impostazioni foto",
            "attr":{
                "priority":"translate"
            }
        },
        {
            "name":"user_guide_start",
            "value":"Inizia",
            "attr":{
                "priority":"translate"
            }
        },
        {
            "name":"high_quality_desp",
            "value":"Acquisisci immagini da %d MP in modalità Foto. L'elaborazione delle immagini a questa risoluzione potrebbe richiedere tempi leggermente più lunghi.",
            "attr":{
                "priority":"translate"
            }
        },
        {
            "name":"semi_collapsed_guide_change_lens",
            "value":"Tocca due volte per passare da una fotocamera all'altra",
            "attr":{
                "priority":"translate"
            }
        },
        {
            "name":"camera_app_lock_tip",
            "value":"Galleria è bloccata",
            "attr":{
                "priority":"translate"
            }
        },
        {
            "name":"sound_mute",
            "value":"Disattiva audio",
            "attr":{
                "priority":"translate"
            }
        },
        {
            "name":"portrait_effect",
            "value":"Effetti",
            "attr":{
                "priority":"translate"
            }
        },
        {
            "name":"camera_permission_desc",
            "value":"Per scattare foto e registrare video.",
            "attr":{
                "priority":"translate"
            }
        },
        {
            "name":"more",
            "value":"Altro",
            "attr":{
                "priority":"translate"
            }
        },
        {
            "name":"more_restore_layout",
            "value":"Ripristina il layout predefinito",
            "attr":{
                "priority":"translate"
            }
        },
        {
            "name":"camera_app_lock_go_to_photo",
            "value":"Sblocca e accedi",
            "attr":{
                "priority":"translate"
            }
        },
        {
            "name":"camera_error_title",
            "value":"Errore Fotocamera",
            "attr":{
                "priority":"translate"
            }
        },
        {
            "name":"professional_photo_mode",
            "value":"Professionista",
            "attr":{
                "priority":"translate"
            }
        },
        {
            "name":"timer_5_seconds",
            "value":"%d secondi",
            "attr":{
                "priority":"translate"
            }
        },
        {
            "name":"self_mirror",
            "value":"Effetto specchio",
            "attr":{
                "priority":"translate"
            }
        },
        {
            "name":"video_mode",
            "value":"Video",
            "attr":{
                "priority":"translate"
            }
        },
        {
            "name":"macro_mode",
            "value":"Super macro",
            "attr":{
                "priority":"translate"
            }
        },
        {
            "name":"no_photos_and_videos",
            "value":"Nessuna foto o video",
            "attr":{
                "priority":"translate"
            }
        },
        {
            "name":"confirm",
            "value":"OK",
            "attr":{
                "priority":"translate"
            }
        },
        {
            "name":"high_quality",
            "value":"Migliora le immagini",
            "attr":{
                "priority":"translate"
            }
        },
        {
            "name":"professional_mode",
            "value":"Professionista",
            "attr":{
                "priority":"translate"
            }
        },
        {
            "name":"portrait_beauty",
            "value":"Bellezza",
            "attr":{
                "priority":"translate"
            }
        },
        {
            "name":"assistive_grid",
            "value":"Griglia fotocamera",
            "attr":{
                "priority":"translate"
            }
        },
        {
            "name":"night_capture_desc",
            "value":"Tieni fermo il dispositivo.\nAttendi il conto alla rovescia o tocca l'otturatore per scattare una foto.",
            "attr":{
                "priority":"translate"
            }
        },
        {
            "name":"part_change_exposure_focus",
            "value":"Trascina il quadrato per regolare la messa a fuoco e il cerchio per regolare la misurazione.",
            "attr":{
                "priority":"translate"
            }
        },
        {
            "name":"restore_defaults",
            "value":"Ripristina predefinite",
            "attr":{
                "priority":"translate"
            }
        },
        {
            "name":"mode_slow",
            "value":"Slow motion",
            "attr":{
                "priority":"translate"
            }
        },
        {
            "name":"geo_location_desp",
            "value":"Tagga foto e video con le informazioni sulla posizione.",
            "attr":{
                "priority":"translate"
            }
        },
        {
            "name":"no_photos_and_videos_desc",
            "value":"Scatta foto e video con la Fotocamera o sblocca il dispositivo per accedere alla Galleria.",
            "attr":{
                "priority":"translate"
            }
        },
        {
            "name":"professional_video_mode",
            "value":"Professionista",
            "attr":{
                "priority":"translate"
            }
        },
        {
            "name":"confirm_restore_message",
            "value":"Le impostazioni della Fotocamera verranno ripristinate sui valori predefiniti.",
            "attr":{
                "priority":"translate"
            }
        },
        {
            "name":"highPixel_mode",
            "value":"Alta risoluzione",
            "attr":{
                "priority":"translate"
            }
        },
        {
            "name":"timer_10_seconds",
            "value":"%d secondi",
            "attr":{
                "priority":"translate"
            }
        },
        {
            "name":"semi_collapsed_guide_take_photo",
            "value":"Tocca per scattare una foto o registrare un video",
            "attr":{
                "priority":"translate"
            }
        },
        {
            "name":"general",
            "value":"Generali",
            "attr":{
                "priority":"translate"
            }
        },
        {
            "name":"more_tip_context",
            "value":"Trascina le icone per regolare il layout",
            "attr":{
                "priority":"translate"
            }
        },
        {
            "name":"cannot_connect_camera",
            "value":"Impossibile collegarsi alla fotocamera.",
            "attr":{
                "priority":"translate"
            }
        },
        {
            "name":"semi_collapsed_guide_capture",
            "value":"Ruota il telefono per ottenere risultati migliori",
            "attr":{
                "priority":"translate"
            }
        },
        {
            "name":"aspect_ratio",
            "value":"Proporzione",
            "attr":{
                "priority":"translate"
            }
        },
        {
            "name":"hdr_vivid",
            "value":"HDR Vivid",
            "attr":{
                "priority":"translate"
            }
        },
        {
            "name":"cancel",
            "value":"Annulla",
            "attr":{
                "priority":"translate"
            }
        },
        {
            "name":"edit",
            "value":"Modifica",
            "attr":{
                "priority":"translate"
            }
        },
        {
            "name":"imagevideo_permission_desc",
            "value":"Per visualizzare e archiviare le foto che scatti e i video che riprendi.",
            "attr":{
                "priority":"translate"
            }
        },
        {
            "name":"user_guide_next",
            "value":"Avanti",
            "attr":{
                "priority":"translate"
            }
        },
        {
            "name":"already_on",
            "value":"On",
            "attr":{
                "priority":"translate"
            }
        },
        {
            "name":"timer",
            "value":"Timer",
            "attr":{
                "priority":"translate"
            }
        },
        {
            "name":"settings",
            "value":"Impostazioni",
            "attr":{
                "priority":"translate"
            }
        }
    ]
}